Workbook

Sheet Cleaned Data
A1: Sales Dataset — Cleaned Data
A2: 240 sales orders from January 2 through June 29, 2026. Source fields are preserved; the final column validates each order total.
A4: Order Id | B4: Date | C4: Product | D4: Quantity | E4: Unit Price | F4: Total | G4: Region | H4: Salesperson | I4: Total Check
A5: SO-1001 | B5: 46146 | C5: Mechanical Keyboard | D5: 6 | E5: 112.7 | F5: 676.2 | G5: North | H5: Sofia Kowalski | I5: =IF(ABS(F5-D5*E5)<0.011,"OK","Check") -> OK
A6: SO-1002 | B6: 46199 | C6: USB-C Hub | D6: 6 | E6: 35.78 | F6: 214.68 | G6: South | H6: Sofia Kowalski | I6: =IF(ABS(F6-D6*E6)<0.011,"OK","Check") -> OK
A7: SO-1003 | B7: 46089 | C7: Standing Desk | D7: 1 | E7: 111.15 | F7: 111.15 | G7: South | H7: Elena Cohen | I7: =IF(ABS(F7-D7*E7)<0.011,"OK","Check") -> OK
A8: SO-1004 | B8: 46067 | C8: Webcam 1080p | D8: 1 | E8: 112.67 | F8: 112.67 | G8: East | H8: Omar Haddad | I8: =IF(ABS(F8-D8*E8)<0.011,"OK","Check") -> OK
A9: SO-1005 | B9: 46075 | C9: Webcam 1080p | D9: 1 | E9: 54.09 | F9: 54.09 | G9: Central | H9: Sofia Kowalski | I9: =IF(ABS(F9-D9*E9)<0.011,"OK","Check") -> OK
A10: SO-1006 | B10: 46040 | C10: Desk Lamp | D10: 4 | E10: 215.54 | F10: 862.16 | G10: West | H10: Omar Haddad | I10: =IF(ABS(F10-D10*E10)<0.011,"OK","Check") -> OK
A11: SO-1007 | B11: 46125 | C11: Cable Organizer | D11: 3 | E11: 17.52 | F11: 52.56 | G11: East | H11: Tomás Tanaka | I11: =IF(ABS(F11-D11*E11)<0.011,"OK","Check") -> OK
A12: SO-1008 | B12: 46148 | C12: Noise-Cancelling Headphones | D12: 6 | E12: 181.65 | F12: 1089.9 | G12: West | H12: Omar Haddad | I12: =IF(ABS(F12-D12*E12)<0.011,"OK","Check") -> OK
A13: SO-1009 | B13: 46116 | C13: Laptop Stand | D13: 8 | E13: 28.72 | F13: 229.76 | G13: East | H13: Sofia Kowalski | I13: =IF(ABS(F13-D13*E13)<0.011,"OK","Check") -> OK
A14: SO-1010 | B14: 46082 | C14: Ergonomic Chair | D14: 7 | E14: 143.97 | F14: 1007.79 | G14: East | H14: Priya Herrera | I14: =IF(ABS(F14-D14*E14)<0.011,"OK","Check") -> OK
A15: SO-1011 | B15: 46049 | C15: Cable Organizer | D15: 7 | E15: 147.79 | F15: 1034.53 | G15: North | H15: Priya Herrera | I15: =IF(ABS(F15-D15*E15)<0.011,"OK","Check") -> OK
A16: SO-1012 | B16: 46161 | C16: Wireless Mouse | D16: 5 | E16: 206.67 | F16: 1033.35 | G16: North | H16: Chen Bennett | I16: =IF(ABS(F16-D16*E16)<0.011,"OK","Check") -> OK
... A244: SO-1240 | B244: 46116 | C244: Webcam 1080p | D244: 6 | E244: 160.47 | F244: 962.82 | G244: Central | H244: Chen Bennett | I244: =IF(ABS(F244-D244*E244)<0.011,"OK","Check") -> OK

Sheet Calculations
A1: Sales Analysis — Calculations
A2: Formula-based KPIs linked to Cleaned Data. Verified Result provides the current result for easy checking.
A4: Metric | B4: Excel Formula | C4: Verified Result | D4: Interpretation
A5: Total Revenue | B5: =SUM('Cleaned Data'!F5:F244) -> 142437.14 | C5: 142437.14 | D5: Total sales value across all orders.
A6: Number of Orders | B6: =COUNTA('Cleaned Data'!A5:A244) -> 240 | C6: 240 | D6: Count of order records.
A7: Units Sold | B7: =SUM('Cleaned Data'!D5:D244) -> 1108 | C7: 1108 | D7: Total number of items sold.
A8: Average Order Value | B8: =AVERAGE('Cleaned Data'!F5:F244) -> 593.48808 | C8: 593.48808 | D8: Average revenue per order.
A9: Average Quantity per Order | B9: =AVERAGE('Cleaned Data'!D5:D244) -> 4.6166667 | C9: 4.6166667 | D9: Average units per order.
A10: Highest Order Value | B10: =MAX('Cleaned Data'!F5:F244) -> 1779.92 | C10: 1779.92 | D10: Largest order total.
A11: Lowest Order Value | B11: =MIN('Cleaned Data'!F5:F244) -> 10.1 | C11: 10.1 | D11: Smallest order total.
A12: Unique Products | B12: =COUNTA('Summary Tables'!A6:A17) -> 12 | C12: 12 | D12: Number of product types.
A13: Unique Regions | B13: =COUNTA('Summary Tables'!F6:F10) -> 5 | C13: 5 | D13: Number of regions.
A14: Unique Salespeople | B14: =COUNTA('Summary Tables'!K6:K11) -> 6 | C14: 6 | D14: Number of salespeople.
A15: Blank Cells in Source Fields | B15: =COUNTBLANK('Cleaned Data'!A5:H244) -> 0 | C15: 0 | D15: Missing values in the original eight fields.
A16: Duplicate Order IDs | B16: =SUMPRODUCT(--(COUNTIF('Cleaned Data'!A5:A244,'Cleaned Data'!A5:A244)>1)) -> 0 | C16: 0 | D16: Rows with repeated order IDs; expected to be zero.
A17: Total Calculation Errors | B17: =COUNTIF('Cleaned Data'!I5:I244,"Check") -> 0 | C17: 0 | D17: Checks quantity × unit price against total.

Sheet Summary Tables
A1: Sales Summary Tables
A2: Summaries by product, region, salesperson, and month. Revenue shares and monthly changes are formula-based.
A4: By Product | F4: By Region | K4: By Salesperson
A5: Product | B5: Orders | C5: Units Sold | D5: Revenue | E5: Revenue Share | F5: Region | G5: Orders | H5: Units Sold | I5: Revenue | J5: Revenue Share | K5: Salesperson | L5: Orders | M5: Units Sold | N5: Revenue | O5: Revenue Share
A6: Laptop Stand | B6: 24 | C6: 133 | D6: 18713.9 | E6: =D6/Calculations!$C$5 -> 0.13138357 | F6: Central | G6: 50 | H6: 215 | I6: 30787.94 | J6: =I6/Calculations!$C$5 -> 0.21615107 | K6: Priya Herrera | L6: 45 | M6: 218 | N6: 28195.51 | O6: =N6/Calculations!$C$5 -> 0.19795055
A7: Webcam 1080p | B7: 28 | C7: 122 | D7: 16809.84 | E7: =D7/Calculations!$C$5 -> 0.11801585 | F7: South | G7: 42 | H7: 230 | I7: 30083.51 | J7: =I7/Calculations!$C$5 -> 0.21120552 | K7: Sofia Kowalski | L7: 46 | M7: 202 | N7: 24885.19 | O7: =N7/Calculations!$C$5 -> 0.17470998
A8: Cable Organizer | B8: 24 | C8: 113 | D8: 16142.37 | E8: =D8/Calculations!$C$5 -> 0.11332978 | F8: North | G8: 46 | H8: 225 | I8: 28925 | J8: =I8/Calculations!$C$5 -> 0.20307204 | K8: Tomás Tanaka | L8: 38 | M8: 183 | N8: 24112.18 | O8: =N8/Calculations!$C$5 -> 0.16928296
A9: Wireless Mouse | B9: 22 | C9: 102 | D9: 14290.77 | E9: =D9/Calculations!$C$5 -> 0.10033036 | F9: East | G9: 52 | H9: 214 | I9: 26485.82 | J9: =I9/Calculations!$C$5 -> 0.18594743 | K9: Omar Haddad | L9: 35 | M9: 168 | N9: 22989.34 | O9: =N9/Calculations!$C$5 -> 0.1613999
A10: External SSD 1TB | B10: 20 | C10: 97 | D10: 12103.9 | E10: =D10/Calculations!$C$5 -> 0.084977134 | F10: West | G10: 50 | H10: 224 | I10: 26154.87 | J10: =I10/Calculations!$C$5 -> 0.18362395 | K10: Elena Cohen | L10: 40 | M10: 164 | N10: 21737.26 | O10: =N10/Calculations!$C$5 -> 0.15260949
A11: Noise-Cancelling Headphones | B11: 18 | C11: 79 | D11: 10674.32 | E11: =D11/Calculations!$C$5 -> 0.074940567 | K11: Chen Bennett | L11: 36 | M11: 173 | N11: 20517.66 | O11: =N11/Calculations!$C$5 -> 0.14404712
A12: Ergonomic Chair | B12: 24 | C12: 98 | D12: 10624.93 | E12: =D12/Calculations!$C$5 -> 0.074593817
A13: Desk Lamp | B13: 15 | C13: 71 | D13: 10445.8 | E13: =D13/Calculations!$C$5 -> 0.07333621
A14: Mechanical Keyboard | B14: 15 | C14: 75 | D14: 9513.33 | E14: =D14/Calculations!$C$5 -> 0.066789673
A15: 27-inch Monitor | B15: 18 | C15: 76 | D15: 8509.33 | E15: =D15/Calculations!$C$5 -> 0.05974095
A16: USB-C Hub | B16: 16 | C16: 77 | D16: 8082.1 | E16: =D16/Calculations!$C$5 -> 0.056741521
A17: Standing Desk | B17: 16 | C17: 65 | D17: 6526.55 | E17: =D17/Calculations!$C$5 -> 0.045820563
A22: Monthly Sales Summary
A23: Month | B23: Orders | C23: Units Sold | D23: Revenue | E23: Revenue Change
A24: 46023 | B24: 40 | C24: 184 | D24: 24177.45 | E24: N/A
A25: 46054 | B25: 29 | C25: 126 | D25: 13788.89 | E25: =D25/D24-1 -> -0.42967972
A26: 46082 | B26: 39 | C26: 170 | D26: 19390.28 | E26: =D26/D25-1 -> 0.40622487
A27: 46113 | B27: 43 | C27: 203 | D27: 23471.38 | E27: =D27/D26-1 -> 0.21047143
A28: 46143 | B28: 39 | C28: 188 | D28: 24885.97 | E28: =D28/D27-1 -> 0.060268719
A29: 46174 | B29: 50 | C29: 237 | D29: 36723.17 | E29: =D29/D28-1 -> 0.47565757

Sheet Charts
A1: Sales Charts
A2: Charts linked to the summary tables for product, regional, monthly, and salesperson comparisons.

Sheet Analysis
A1: Sales Data Analysis
A2: Key findings based on 240 sales orders recorded from January 2 through June 29, 2026.
A4: Overall Sales | B4: Total revenue was $142,437.14 across 240 orders, with 1,108 units sold. Average order value was $593.49.
A5: Top Product by Revenue | B5: Laptop Stand generated $18,713.90 across 24 orders and 133 units, the highest product revenue.
A6: Lowest Product by Revenue | B6: Standing Desk generated $6,526.55; review its pricing, demand, bundling opportunities, and product visibility before changing stock levels.
A7: Regional Performance | B7: Central had the highest regional revenue at $30,787.94. West had the lowest at $26,154.87.
A8: Salesperson Performance | B8: Priya Herrera recorded the highest revenue at $28,195.51. Chen Bennett recorded $20,517.66; compare order volume and product mix before evaluating performance.
A9: Monthly Trend | B9: June 2026 was the highest-revenue month ($36,723.17); February 2026 was the lowest ($13,788.89). June revenue was 47.6% higher than May.
A10: Data Quality | B10: No blank values or duplicate order IDs were found in the source fields, and all 240 order totals match quantity × unit price within one cent.
A11: Interpretation Note | B11: The dataset does not include costs, discounts, returns, profit margins, customer details, or marketing spend. Revenue should not be treated as profit, and the causes of monthly changes cannot be confirmed from these fields alone.

Sheet Recommendations
A1: Recommendations
A2: Actionable suggestions based on observed sales patterns; these are recommendations, not confirmed causes.
A4: Priority | B4: Recommendation | C4: Reason / Suggested Action
A5: High | B5: Maintain availability of top-revenue products | C5: Laptop Stand led revenue at $18,713.90. Monitor stock levels and avoid preventable stockouts.
A6: High | B6: Investigate the June sales increase | C6: June revenue was 47.6% above May. Check promotions, seasonal demand, order mix, and stock availability.
A7: Medium | B7: Review lower-revenue product performance | C7: Standing Desk had the lowest revenue. Compare units sold, margin, holding cost, and customer demand before changing price or inventory.
A8: Medium | B8: Study regional differences | C8: Central led regional revenue while West had the lowest. Review product availability, order size, and sales activity.
A9: Medium | B9: Share effective sales practices | C9: Priya Herrera recorded the highest revenue. Compare order mix and selling practices, accounting for differences in order volume and assignments.
A10: Medium | B10: Track profit and cost metrics | C10: Add purchase cost, operating expenses, discounts, returns, and gross margin to future records. Revenue alone cannot show profitability.
A11: Low | B11: Use a recurring monthly dashboard | C11: Refresh summaries to monitor revenue, units sold, average order value, and changes by region, product, and salesperson.
